pipelining/__init__.py
pipelining/graphing.py
pipelining/running.py
pipelining/stages.py
pipelining/stats.py
pipelining/structure.py
pipelining/testing.py
pipelining-0.11.6.dist-info/METADATA
pipelining-0.11.6.dist-info/WHEEL
pipelining-0.11.6.dist-info/top_level.txt
pipelining-0.11.6.dist-info/RECORD
