Metadata-Version: 2.1
Name: pipelining
Version: 0.11.6
Summary: Declarative pipelines on top of python multiprocessing artifacts
Home-page: UNKNOWN
License: UNKNOWN
Platform: UNKNOWN
Requires-Python: >=3
